textify/__init__.py
textify/textify.py
textify-0.0.1.dist-info/LICENSE
textify-0.0.1.dist-info/WHEEL
textify-0.0.1.dist-info/METADATA
textify-0.0.1.dist-info/RECORD
