Metadata-Version: 2.1
Name: textify
Version: 0.0.1
Summary: A Simple Text Cleaning Package  For cleaning text during NLP
Home-page: https://github.com/Jcharis/textify
License: MIT
Keywords: textify,jcharistech,clean text,NLP,text preprocessing,text cleaning
Author: Jesse E.Agbe(JCharis)
Author-email: jcharistech@gmail.com
Requires-Python: >=3.7,<4.0
Classifier: License :: OSI Approved :: MIT License
Classifier: Operating System :: OS Independent
Classifier: Programming Language :: Python :: 3
Classifier: Programming Language :: Python :: 3.7
Classifier: Programming Language :: Python :: 3.8
Project-URL: Repository, https://github.com/Jcharis/textify
